doc_template_cloner/__init__.py
doc_template_cloner/utils.py
doc_template_cloner-0.2.3.dist-info/LICENSE
doc_template_cloner-0.2.3.dist-info/METADATA
doc_template_cloner-0.2.3.dist-info/WHEEL
doc_template_cloner-0.2.3.dist-info/top_level.txt
doc_template_cloner-0.2.3.dist-info/RECORD
