Metadata-Version: 2.1
Name: doc_template_cloner
Version: 0.2.3
Summary: Custom lib to clone lebaling from one image to another similar.
Home-page: https://github.com/bilykigor/doc_template_cloner
Author: Ihor Bilyk
License: Apache License 2.0
Keywords: Custom lib to clone lebaling from one image to another similar
Classifier: Development Status :: 5 - Production/Stable
Classifier: Intended Audience :: Developers
Classifier: Natural Language :: English
Classifier: License :: OSI Approved :: Apache Software License
Classifier: Programming Language :: Python
Classifier: Programming Language :: Python :: 3.7
Classifier: Programming Language :: Python :: 3.8
Classifier: Programming Language :: Python :: 3.9
Classifier: Programming Language :: Python :: 3.10
Requires-Python: >= 3.6
License-File: LICENSE
Requires-Dist: pandas
Requires-Dist: doc2graph ==2.2.5
